pinit/.pinit/install.py
pinit/.pinit/main.py
pinit/.pinit/pinit.svg
pinit/.pinit/requirements.txt
pinit/.pinit/shortcut.py
pinit/.pinit/ui/assets/index-68b1541e.js
pinit/.pinit/ui/assets/index-a348a599.css
pinit/.pinit/ui/assets/w-af655217.woff2
pinit/.pinit/ui/icon.svg
pinit/.pinit/ui/index.html
pinit/.pinit/uninstall.py
pinit/.pinit/upgrade.py
pinit/__init__.py
pinit/main.py
pinit-0.0.29.dist-info/METADATA
pinit-0.0.29.dist-info/WHEEL
pinit-0.0.29.dist-info/entry_points.txt
pinit-0.0.29.dist-info/RECORD
